.coverage
.env.example
.gitignore
.readthedocs.yaml
LICENSE
README.md
environment.yml
pyproject.toml
.github/workflows/lint.yml
.github/workflows/python.yml
docs/.gitignore
docs/Makefile
docs/conf.py
docs/credits.rst
docs/docs_fig_L2_vs_L3.png
docs/docs_fig_col_insitu.png
docs/docs_fig_gridder_coll_nov.png
docs/docs_fig_gridder_coll_rmse.png
docs/docs_fig_gridder_obs.png
docs/docs_fig_sat_quicklook_001.png
docs/docs_fig_sat_quicklook_002.png
docs/docs_fig_sat_quicklook_003.png
docs/docs_fig_sat_quicklook_004.png
docs/docs_fig_sat_quicklook_005.png
docs/docs_fig_sat_vs_mod_waves.png
docs/docs_fig_sat_vs_mod_wind.png
docs/docs_fig_sat_waves.png
docs/docs_fig_sat_wind.png
docs/docs_fig_stormtrack.png
docs/docs_fig_tc_1.png
docs/docs_fig_tc_2.png
docs/docs_fig_ts_insitu.png
docs/docs_fig_ts_sat.png
docs/ecwamMoz_coll_2023_map.png
docs/ecwamMoz_coll_2023_sc.png
docs/ecwamMoz_coll_2023_ts.png
docs/explore_retrieval.png
docs/gallery.rst
docs/index.rst
docs/installation.rst
docs/ipynb_find_env.png
docs/lm_example.png
docs/lm_example_coast.png
docs/lm_example_coast_norway.png
docs/model_quicklook.png
docs/mozambique23.rst
docs/mozambique24.rst
docs/mozambique25.rst
docs/mozambique_example_global_ipynb.png
docs/mozambique_example_global_ipynb_crop.png
docs/mozambique_example_region_ipynb_crop.png
docs/oneocean.rst
docs/oslo_ws24_collocated_ts.png
docs/oslo_ws24_filters_1.png
docs/oslo_ws24_filters_2.png
docs/oslo_ws24_filters_3.png
docs/oslo_ws24_filters_4.png
docs/oslo_ws24_filters_sat_map_despike.png
docs/oslo_ws24_filters_sat_map_limits.png
docs/oslo_ws24_filters_sat_map_raw.png
docs/oslo_ws24_filters_sat_map_smooth.png
docs/oslo_ws24_filters_sat_ts_despike.png
docs/oslo_ws24_filters_sat_ts_limits.png
docs/oslo_ws24_filters_sat_ts_raw.png
docs/oslo_ws24_filters_sat_ts_smooth.png
docs/oslo_ws24_filters_sat_xtrack.png
docs/oslo_ws24_gridding_map.png
docs/oslo_ws24_gridding_nb_collocated.png
docs/oslo_ws24_gridding_rmsd.png
docs/oslo_ws24_insitu.png
wavyopen.egg-info/PKG-INFO
wavyopen.egg-info/SOURCES.txt
wavyopen.egg-info/dependency_links.txt
wavyopen.egg-info/entry_points.txt
wavyopen.egg-info/requires.txt
wavyopen.egg-info/top_level.txt