Metadata-Version: 2.4
Name: wavyopen
Version: 0.5.8
Summary: A package for processing/calibrating/validating wave measurements and wave model output.
Author-email: Patrik Bohlinger <patrikb@met.no>
License-Expression: MIT
Requires-Python: >=3.12
License-File: LICENSE
Requires-Dist: matplotlib>=3.5
Requires-Dist: numpy>=1.20
Requires-Dist: scipy<1.17
Requires-Dist: netCDF4>=1.6
Requires-Dist: pyyaml>=6
Requires-Dist: pyproj>=2.3
Requires-Dist: cmocean>=3
Requires-Dist: joblib>=1.4
Requires-Dist: pandas>=2.2
Requires-Dist: xarray>=2024
Requires-Dist: pyresample>=1.30
Requires-Dist: geojson>=2.5
Requires-Dist: Cartopy>=0.20
Requires-Dist: pyGAM>=0.9
Requires-Dist: roaring-landmask>=0.7
Requires-Dist: copernicusmarine>=2.0
Requires-Dist: xdg
Requires-Dist: tqdm>=4
Requires-Dist: python-dotenv
Requires-Dist: click
Requires-Dist: scikit-learn>=1.6
Requires-Dist: fsspec
Requires-Dist: requests
Requires-Dist: aiohttp
Requires-Dist: dill
Requires-Dist: geopandas
Dynamic: license-file
